pymsbuild_winui-0.0.1a9.dist-info/WHEEL
pymsbuild_winui-0.0.1a9.dist-info/METADATA
pymsbuild_winui/generate.py
pymsbuild_winui/__init__.py
pymsbuild_winui/pymsbuild.py
pymsbuild_winui/_controldata.py
pymsbuild_winui/targets/winui_Windows_Foundation_Collections.cpp
pymsbuild_winui/targets/winui.targets
pymsbuild_winui/targets/winui.props
pymsbuild_winui/targets/_winui.h
pymsbuild_winui/targets/winui_Windows_Foundation.cpp
pymsbuild_winui/targets/restore.py
pymsbuild_winui/targets/python-winui.h
pymsbuild_winui/templates/page.xaml.cpp.in
pymsbuild_winui/templates/app.xaml.cpp.in
pymsbuild_winui/templates/page.xaml.h.in
pymsbuild_winui/templates/app.idl.in
pymsbuild_winui/templates/page.idl.in
pymsbuild_winui/templates/regen-header.tmpl
pymsbuild_winui/templates/app.manifest.in
pymsbuild_winui/templates/app.xaml.h.in
pymsbuild_winui-0.0.1a9.dist-info/RECORD